cryptoadvance/specterext/stacktrack/__init__.py
cryptoadvance/specterext/stacktrack/__main__.py
cryptoadvance/specterext/stacktrack/_version.py
cryptoadvance/specterext/stacktrack/app_config.py
cryptoadvance/specterext/stacktrack/config.py
cryptoadvance/specterext/stacktrack/controller.py
cryptoadvance/specterext/stacktrack/service.py
cryptoadvance/specterext/stacktrack/helpers/__init__.py
cryptoadvance/specterext/stacktrack/helpers/core.py
cryptoadvance/specterext/stacktrack/helpers/dtutil.py
cryptoadvance/specterext/stacktrack/helpers/plot.py
cryptoadvance/specterext/stacktrack/static/stacktrack/css/styles.css
cryptoadvance/specterext/stacktrack/static/stacktrack/img/chart.png
cryptoadvance/specterext/stacktrack/static/stacktrack/img/ghost.png
cryptoadvance/specterext/stacktrack/static/stacktrack/img/logo.jpeg
cryptoadvance/specterext/stacktrack/templates/stacktrack/base.jinja
cryptoadvance/specterext/stacktrack/templates/stacktrack/index.jinja
cryptoadvance/specterext/stacktrack/templates/stacktrack/wallet/chart/wallet_chart.jinja
cryptoadvance/specterext/stacktrack/templates/stacktrack/wallet/components/chart.jinja
cryptoadvance/specterext/stacktrack/templates/stacktrack/wallet/overview/overview_chart_and_tx_table.jinja
specterext_stacktrack-0.3.0.dist-info/LICENSE
specterext_stacktrack-0.3.0.dist-info/METADATA
specterext_stacktrack-0.3.0.dist-info/WHEEL
specterext_stacktrack-0.3.0.dist-info/top_level.txt
specterext_stacktrack-0.3.0.dist-info/RECORD
