Metadata-Version: 2.1
Name: specterext-stacktrack
Version: 0.3.0
Summary: Specter Desktop extension to add time series charts for visualizing wallet balances
Author: Wombat6
License: MIT License
Project-URL: Homepage, https://github.com/cryptoadvance/specterext-stacktrack
Classifier: Programming Language :: Python :: 3
Classifier: License :: OSI Approved :: MIT License
Classifier: Operating System :: OS Independent
Requires-Python: >=3.9
License-File: LICENSE
Requires-Dist: pandas (>=1.3.0)
Requires-Dist: plotly (==5.10.0)
Provides-Extra: test
Requires-Dist: cryptoadvance.specter (>=1.14.5) ; extra == 'test'
Requires-Dist: pytest (>=7.1.3) ; extra == 'test'
Requires-Dist: pytest-cov[all] ; extra == 'test'
